---
layout: post
title: "String的相加"
description: ""
category: 
tags: [JVM,bytecode]
---
{% include JB/setup %}

### 概述

Java本身对String类型做了比较多的封装，而且在编译器层面也对String的操作做了一些处理，所以有些时候对于字符串的处理除了需要从String类型的实现上考虑之外，也需要从编译器的处理上去考虑。

### 问题

之前面试被问到过这样的问题:

{% highlight java %}
		String c = "3"+"4"+"5";
		StringBuilder sb = new StringBuilder();
		sb.append("3").append("4").append("5");
{% endhighlight %}

以上两段代码，哪个的效率更高？

光从表面上看，好像没什么差别。但是实际上还是会存在很大的差别的，因为第一段代码`String c = "3"+"4"+"5"`会在编译器进行优化，直接计算出`c`的值，实际执行的时候只会从常亮池里进行加载。而第二段代码需要新建一个`StringBuilder`对象，并且调用3次`append`方法，所以效率上差别比较大。

但是，这个只是理论上的结论，怎么来证明呢？如果是编译期所做的优化，那么直接看变异后的字节码就可以了。以上代码反编译后的字节码如下：

{% highlight java %}

	  28: ldc           #9                  // String 345
      30: astore_3
      31: new           #3                  // class java/lang/StringBuilder
      34: dup
      35: invokespecial #4                  // Method java/lang/StringBuilder."<init>":()V
      38: astore        4
      40: aload         4
      42: ldc           #10                 // String 3
      44: invokevirtual #5                  // Method java/lang/StringBuilder.append:(Ljava/lang/String;)Ljava/lang/StringBuilder;
      47: ldc           #11                 // String 4
      49: invokevirtual #5                  // Method java/lang/StringBuilder.append:(Ljava/lang/String;)Ljava/lang/StringBuilder;
      52: ldc           #12                 // String 5
      54: invokevirtual #5                  // Method java/lang/StringBuilder.append:(Ljava/lang/String;)Ljava/lang/StringBuilder;

{% endhighlight %}

上面的第一行`ldc #9 // String 345`就是表示加载`345`这个常亮，`astore_3`就是赋值给变量`c`。下面的一段就是后面的代码了，基本上是java代码一句一句的翻译，没有任何优化。所以前面的代码效率要高。

那么，接下来看第二个问题，还是两段代码，哪个效率更高？

{% highlight java %}
	String a = "3";
	String b = a + "4"+"5";

	StringBuilder sb = new StringBuilder();
	sb.append(a).append("4").append("5");
{% endhighlight %}

这个问题我当时思考了一段时间，感觉上差不多，但是因为一般的问题都会有个差别的答案的，后来验证一下，其实当时自己的结论是正确的，因为这里的`b`不再是常亮，所以编译器不会进行优化，但是编译器会做的优化是把String的`+`转换成用StringBuilder来实现。所以也就是说，其实上面的两段代码是等效的。直接看反编译后的字节码：

{% highlight java %}
 0: ldc           #2                  // String 3
       2: astore_1
       3: new           #3                  // class java/lang/StringBuilder
       6: dup
       7: invokespecial #4                  // Method java/lang/StringBuilder."<init>":()V
      10: aload_1
      11: invokevirtual #5                  // Method java/lang/StringBuilder.append:(Ljava/lang/String;)Ljava/lang/StringBuilder;
      14: ldc           #6                  // String 4
      16: invokevirtual #5                  // Method java/lang/StringBuilder.append:(Ljava/lang/String;)Ljava/lang/StringBuilder;
      19: ldc           #7                  // String 5
      21: invokevirtual #5                  // Method java/lang/StringBuilder.append:(Ljava/lang/String;)Ljava/lang/StringBuilder;
      24: invokevirtual #8                  // Method java/lang/StringBuilder.toString:()Ljava/lang/String;
      27: astore_2
      28: new           #3                  // class java/lang/StringBuilder
      31: dup
      32: invokespecial #4                  // Method java/lang/StringBuilder."<init>":()V
      35: astore_3
      36: aload_3
      37: aload_1
      38: invokevirtual #5                  // Method java/lang/StringBuilder.append:(Ljava/lang/String;)Ljava/lang/StringBuilder;
      41: ldc           #6                  // String 4
      43: invokevirtual #5                  // Method java/lang/StringBuilder.append:(Ljava/lang/String;)Ljava/lang/StringBuilder;
      46: ldc           #7                  // String 5
      48: invokevirtual #5                  // Method java/lang/StringBuilder.append:(Ljava/lang/String;)Ljava/lang/StringBuilder;

{% endhighlight %}

最终的结论可以直接从StringBuilder的几个方法上来得出，都是调用来一次构造方法和3次`append`方法。



